nasa_csda/__init__.py
nasa_csda/buffer.py
nasa_csda/cli.py
nasa_csda/client.py
nasa_csda/config.py
nasa_csda/models/__init__.py
nasa_csda/models/bulk_download.py
nasa_csda/models/item_collection.py
nasa_csda/models/link.py
nasa_csda/models/search.py
nasa_csda/py.typed
nasa_csda/streaming.py
nasa_csda/transport.py
nasa_csda-1.3.2.dist-info/LICENSE
nasa_csda-1.3.2.dist-info/METADATA
nasa_csda-1.3.2.dist-info/WHEEL
nasa_csda-1.3.2.dist-info/entry_points.txt
nasa_csda-1.3.2.dist-info/RECORD
