Metadata-Version: 2.3
Name: nasa-csda
Version: 1.3.2
Summary: 
Keywords: Development Status :: 5 - Stable,License :: OSI Approved :: MIT License,Programming Language :: Python :: 3.9,Programming Language :: Python :: 3.10,Programming Language :: Python :: 3.11,Programming Language :: Python :: 3.12
Author: Your Name
Author-email: you@example.com
Requires-Python: >=3.9,<4.0
Classifier: Programming Language :: Python :: 3
Classifier: Programming Language :: Python :: 3.9
Classifier: Programming Language :: Python :: 3.10
Classifier: Programming Language :: Python :: 3.11
Classifier: Programming Language :: Python :: 3.12
Classifier: Programming Language :: Python :: 3.13
Requires-Dist: aiostream (>=0.6.2,<0.7.0)
Requires-Dist: asyncclick (>=8.1.7.2,<9.0.0.0)
Requires-Dist: cachetools (>=5.4.0,<6.0.0)
Requires-Dist: click (>=8.1.7,<9.0.0)
Requires-Dist: httpx[http2] (>=0.27.0,<0.28.0)
Requires-Dist: platformdirs (>=4.2.2,<5.0.0)
Requires-Dist: pydantic (>=2.8.2,<3.0.0)
Requires-Dist: pydantic-settings (>=2.4.0,<3.0.0)
Requires-Dist: python-dateutil (>=2.9.0.post0,<3.0.0)
Requires-Dist: stac-pydantic (>=3.1.1,<4.0.0)
Requires-Dist: tenacity (>=9.0.0,<10.0.0)
Requires-Dist: tqdm (>=4.66.4,<5.0.0)
